README.rst
setup.py
cythereal_vbsdk.egg-info/PKG-INFO
cythereal_vbsdk.egg-info/SOURCES.txt
cythereal_vbsdk.egg-info/dependency_links.txt
cythereal_vbsdk.egg-info/entry_points.txt
cythereal_vbsdk.egg-info/requires.txt
cythereal_vbsdk.egg-info/top_level.txt
vbsdk/__init__.py
vbsdk/progress.py
vbsdk/vbregister.py
vbsdk/vbsdk.py
vbsdk/virusbattle.py
vbsdk/actions/__init__.py
vbsdk/actions/processors/__init__.py
vbsdk/actions/processors/query.py
vbsdk/actions/processors/search.py
vbsdk/actions/processors/upload.py
vbsdk/actions/visitors/__init__.py
vbsdk/actions/visitors/avscan.py
vbsdk/actions/visitors/download.py
vbsdk/actions/visitors/map.py
vbsdk/actions/visitors/matches.py
vbsdk/actions/visitors/pooledReprocess.py
vbsdk/actions/visitors/pooledUpload.py
vbsdk/actions/visitors/progressMonitor.py
vbsdk/actions/visitors/query.py
vbsdk/actions/visitors/query2file.py
vbsdk/actions/visitors/reprocess.py
vbsdk/vbBase/__init__.py
vbsdk/vbBase/helper.py
vbsdk/vbBase/types.py
vbsdk/vbBase/vbBase.py