Metadata-Version: 1.1
Name: cythereal-vbsdk
Version: 0.4.0
Summary: Client for accessing Cythereal Virusbattle and MAGIC
Home-page: https://bitbucket.org/cythereal/virusbattle-sdk/src
Author: Cythereal
Author-email: webmaster@cythereal.com
License: Apache Software License 2.0
Platform: UNKNOWN
Classifier: Development Status :: 4 - Beta
Classifier: Environment :: Console
Classifier: Intended Audience :: Information Technology
Classifier: Intended Audience :: Developers
Classifier: Intended Audience :: System Administrators
Classifier: Intended Audience :: Science/Research
Classifier: License :: OSI Approved :: Apache Software License
Classifier: Operating System :: POSIX :: Linux
Classifier: Programming Language :: Python :: 2 :: Only
Classifier: Topic :: Security
